speakub/__init__.py
speakub/__main__.py
speakub/_version.py
speakub/cli.py
speakub/desktop.py
speakub/core/__init__.py
speakub/core/bookmarks.py
speakub/core/chapter_manager.py
speakub/core/content_renderer.py
speakub/core/epubkit_adapter.py
speakub/core/exceptions.py
speakub/core/file_validator.py
speakub/core/progress_tracker.py
speakub/core/threading_model.py
speakub/tts/__init__.py
speakub/tts/async_manager.py
speakub/tts/audio_player.py
speakub/tts/circuit_breaker.py
speakub/tts/engine.py
speakub/tts/engine_factory.py
speakub/tts/engine_manager.py
speakub/tts/engine_original.py
speakub/tts/engine_params_manager.py
speakub/tts/error_category_helper.py
speakub/tts/error_recovery_manager.py
speakub/tts/integration.py
speakub/tts/playback_coordinator.py
speakub/tts/playback_manager.py
speakub/tts/playlist_manager.py
speakub/tts/shutdown_coordinator.py
speakub/tts/state_manager.py
speakub/tts/tts_state_machine.py
speakub/tts/backends/__init__.py
speakub/tts/backends/base.py
speakub/tts/backends/mpv_backend.py
speakub/tts/backends/pygame_backend.py
speakub/tts/engines/__init__.py
speakub/tts/engines/edge_tts_provider.py
speakub/tts/engines/gtts_provider.py
speakub/tts/engines/nanmai_tts_provider.py
speakub/tts/fusion_reservoir/__init__.py
speakub/tts/fusion_reservoir/batch_performance_feedback.py
speakub/tts/fusion_reservoir/batching_strategy.py
speakub/tts/fusion_reservoir/controller.py
speakub/tts/ui/__init__.py
speakub/tts/ui/commands.py
speakub/tts/ui/error_handler.py
speakub/tts/ui/network.py
speakub/tts/ui/optimized_bridge.py
speakub/tts/ui/playlist.py
speakub/tts/ui/runners.py
speakub/tts/ui/workers.py
speakub/ui/__init__.py
speakub/ui/actions.py
speakub/ui/app.py
speakub/ui/epub_manager.py
speakub/ui/panel_titles.py
speakub/ui/progress.py
speakub/ui/protocols.py
speakub/ui/tts_panel.py
speakub/ui/ui_utils.py
speakub/ui/voice_selector_panel.py
speakub/ui/screens/__init__.py
speakub/ui/screens/bookmarks.py
speakub/ui/widgets/__init__.py
speakub-2025.12.16.124624.dist-info/METADATA
speakub-2025.12.16.124624.dist-info/WHEEL
speakub-2025.12.16.124624.dist-info/entry_points.txt
speakub-2025.12.16.124624.dist-info/licenses/LICENSE
speakub-2025.12.16.124624.dist-info/RECORD
