Metadata-Version: 2.4
Name: speakub
Version: 2025.12.16.124624
Summary: A rich terminal EPUB reader with TTS support
Project-URL: Homepage, https://github.com/eyes1971/SpeakUB
Project-URL: Repository, https://github.com/eyes1971/SpeakUB.git
Project-URL: Documentation, https://speakub.readthedocs.io/
Project-URL: Bug Tracker, https://github.com/eyes1971/SpeakUB/issues
Author-email: Sam Weng <eyes1971@gmail.com>
License-Expression: MIT
License-File: LICENSE
Keywords: ebook,epub,reader,terminal,text-to-speech,tts
Classifier: Development Status :: 4 - Beta
Classifier: Environment :: Console
Classifier: Intended Audience :: End Users/Desktop
Classifier: Operating System :: OS Independent
Classifier: Programming Language :: Python :: 3
Classifier: Programming Language :: Python :: 3.8
Classifier: Programming Language :: Python :: 3.9
Classifier: Programming Language :: Python :: 3.10
Classifier: Programming Language :: Python :: 3.11
Classifier: Programming Language :: Python :: 3.12
Classifier: Topic :: Text Processing
Classifier: Topic :: Utilities
Requires-Python: >=3.8
Requires-Dist: ebooklib<1.0.0,>=0.18.0
Requires-Dist: epubkit<1.0.0,>=0.1.0
Requires-Dist: html2text<2024.0.0,>=2020.1.16
Requires-Dist: platformdirs<4.0.0,>=3.0.0
Requires-Dist: pydantic<3.0.0,>=2.0.0
Requires-Dist: pyyaml<7.0.0,>=6.0
Requires-Dist: rich<15.0.0,>=14.0.0
Requires-Dist: textual>=1.0.0
Requires-Dist: wcwidth<0.3.0,>=0.2.0
Provides-Extra: all
Requires-Dist: black<24.0,>=22.0; extra == 'all'
Requires-Dist: edge-tts<7.0.0,>=6.1.0; extra == 'all'
Requires-Dist: fabulous<1.0.0,>=0.1.0; extra == 'all'
Requires-Dist: flake8<7.0,>=4.0; extra == 'all'
Requires-Dist: mypy<2.0,>=0.900; extra == 'all'
Requires-Dist: pillow<11.0.0,>=8.0.0; extra == 'all'
Requires-Dist: pre-commit<4.0,>=2.0; extra == 'all'
Requires-Dist: pygame<3.0.0,>=2.0.0; extra == 'all'
Requires-Dist: pytest-asyncio<1.0,>=0.21; extra == 'all'
Requires-Dist: pytest-cov<5.0,>=2.0; extra == 'all'
Requires-Dist: pytest-html<4.0,>=3.0; extra == 'all'
Requires-Dist: pytest-mock<4.0,>=3.10; extra == 'all'
Requires-Dist: pytest-xdist<4.0,>=3.0; extra == 'all'
Requires-Dist: pytest<9.0,>=8.2; extra == 'all'
Provides-Extra: dev
Requires-Dist: black<24.0,>=22.0; extra == 'dev'
Requires-Dist: flake8<7.0,>=4.0; extra == 'dev'
Requires-Dist: mypy<2.0,>=0.900; extra == 'dev'
Requires-Dist: pre-commit<4.0,>=2.0; extra == 'dev'
Requires-Dist: pytest-asyncio<1.0,>=0.21; extra == 'dev'
Requires-Dist: pytest-cov<5.0,>=2.0; extra == 'dev'
Requires-Dist: pytest-html<4.0,>=3.0; extra == 'dev'
Requires-Dist: pytest-mock<4.0,>=3.10; extra == 'dev'
Requires-Dist: pytest-xdist<4.0,>=3.0; extra == 'dev'
Requires-Dist: pytest<9.0,>=8.2; extra == 'dev'
Provides-Extra: images
Requires-Dist: fabulous<1.0.0,>=0.1.0; extra == 'images'
Requires-Dist: pillow<11.0.0,>=8.0.0; extra == 'images'
Provides-Extra: tts
Requires-Dist: edge-tts<7.0.0,>=6.1.0; extra == 'tts'
Requires-Dist: pygame<3.0.0,>=2.0.0; extra == 'tts'
Provides-Extra: tts-all
Requires-Dist: aiohttp<4.0.0,>=3.8.0; extra == 'tts-all'
Requires-Dist: edge-tts<7.0.0,>=6.1.0; extra == 'tts-all'
Requires-Dist: gtts<3.0.0,>=2.3.0; extra == 'tts-all'
Requires-Dist: mutagen<2.0.0,>=1.45.0; extra == 'tts-all'
Requires-Dist: pydub<1.0.0,>=0.25.0; extra == 'tts-all'
Requires-Dist: pygame<3.0.0,>=2.0.0; extra == 'tts-all'
Requires-Dist: python-mpv<2.0.0,>=1.0.0; extra == 'tts-all'
Requires-Dist: requests<3.0.0,>=2.25.0; extra == 'tts-all'
Provides-Extra: tts-gtts
Requires-Dist: edge-tts<7.0.0,>=6.1.0; extra == 'tts-gtts'
Requires-Dist: gtts<3.0.0,>=2.3.0; extra == 'tts-gtts'
Requires-Dist: pygame<3.0.0,>=2.0.0; extra == 'tts-gtts'
Requires-Dist: python-mpv<2.0.0,>=1.0.0; extra == 'tts-gtts'
Provides-Extra: tts-nanmai
Requires-Dist: edge-tts<7.0.0,>=6.1.0; extra == 'tts-nanmai'
Requires-Dist: pygame<3.0.0,>=2.0.0; extra == 'tts-nanmai'
Requires-Dist: python-mpv<2.0.0,>=1.0.0; extra == 'tts-nanmai'
Requires-Dist: requests<3.0.0,>=2.25.0; extra == 'tts-nanmai'
Provides-Extra: tts-nanmai-advanced
Requires-Dist: aiohttp<4.0.0,>=3.8.0; extra == 'tts-nanmai-advanced'
Requires-Dist: edge-tts<7.0.0,>=6.1.0; extra == 'tts-nanmai-advanced'
Requires-Dist: mutagen<2.0.0,>=1.45.0; extra == 'tts-nanmai-advanced'
Requires-Dist: pydub<1.0.0,>=0.25.0; extra == 'tts-nanmai-advanced'
Requires-Dist: pygame<3.0.0,>=2.0.0; extra == 'tts-nanmai-advanced'
Requires-Dist: python-mpv<2.0.0,>=1.0.0; extra == 'tts-nanmai-advanced'
Requires-Dist: requests<3.0.0,>=2.25.0; extra == 'tts-nanmai-advanced'
